pychoice.py
pychoice-0.1.1.dist-info/DESCRIPTION.rst
pychoice-0.1.1.dist-info/METADATA
pychoice-0.1.1.dist-info/RECORD
pychoice-0.1.1.dist-info/WHEEL
pychoice-0.1.1.dist-info/metadata.json
pychoice-0.1.1.dist-info/top_level.txt
