Metadata-Version: 2.0
Name: pychoice
Version: 0.1.1
Summary: An utility adds code readability to your application and/or API, Code is documentation!
Home-page: https://github.com/FuGangqiang/pychoice
Author: FuGangqiang
Author-email: fu_gangqiang@qq.com
License: MIT
Keywords: choice
Platform: UNKNOWN
Classifier: Development Status :: 5 - Production/Stable
Classifier: Programming Language :: Python :: 3 :: Only
Classifier: Programming Language :: Python :: 3.5
Classifier: Programming Language :: Python :: 3.6
Classifier: Topic :: Software Development :: Documentation
Classifier: License :: OSI Approved :: MIT License
